ChromeForTesting/__init__.py
ChromeForTesting/chromelabs.py
ChromeForTesting/config.py
ChromeForTesting/main.py
ChromeForTesting/toolkit.py
robotframework_chromefortesting-0.91.dist-info/LICENSE
robotframework_chromefortesting-0.91.dist-info/METADATA
robotframework_chromefortesting-0.91.dist-info/WHEEL
robotframework_chromefortesting-0.91.dist-info/top_level.txt
robotframework_chromefortesting-0.91.dist-info/RECORD
