Metadata-Version: 2.1
Name: robotframework-chromefortesting
Version: 0.91
Summary: The only extension for seamless setup of Chrome for Testing (CfT) in and within Robot Framework.
Home-page: https://github.com/extraorange/robotframework-chromefortesting
Author: extraorange
Author-email: extraorangeio@pm.me
License: GNU General Public License v3.0
Classifier: Development Status :: 4 - Beta
Classifier: Intended Audience :: Developers
Classifier: License :: OSI Approved :: GNU General Public License v3 (GPLv3)
Classifier: Operating System :: OS Independent
Classifier: Framework :: Robot Framework :: Library
Classifier: Programming Language :: Python :: 3
Classifier: Programming Language :: Python :: 3.6
Classifier: Programming Language :: Python :: 3.7
Classifier: Programming Language :: Python :: 3.8
Classifier: Programming Language :: Python :: 3.9
Classifier: Topic :: Software Development :: Testing
Classifier: Topic :: Software Development :: Testing :: Acceptance
Classifier: Topic :: Software Development :: Testing :: BDD
License-File: LICENSE
Requires-Dist: requests
Requires-Dist: robotframework
